{
  "UserId": 4,
  "FirstName": "Cucuvat",
  "LastName": "Marlena",
  "BoardRows": 2,
  "BoardColumns": 2,
  "Category": 0,
  "RemainingTime": "00:02:44",
  "ElapsedTime": "00:00:00",
  "Cards": [
    {
      "Id": 0,
      "ImagePath": "C:\\Facultate\\An 2\\Semestrul 2\\MAP\\MemoryGame\\MemoryGame\\bin\\Debug\\net8.0-windows\\Images\\Cars\\pexels-charles-kettor-268979-831475.jpg",
      "IsFlipped": false,
      "IsMatched": false
    },
    {
      "Id": 0,
      "ImagePath": "C:\\Facultate\\An 2\\Semestrul 2\\MAP\\MemoryGame\\MemoryGame\\bin\\Debug\\net8.0-windows\\Images\\Cars\\pexels-mikebirdy-244206.jpg",
      "IsFlipped": true,
      "IsMatched": false
    },
    {
      "Id": 0,
      "ImagePath": "C:\\Facultate\\An 2\\Semestrul 2\\MAP\\MemoryGame\\MemoryGame\\bin\\Debug\\net8.0-windows\\Images\\Cars\\pexels-mikebirdy-244206.jpg",
      "IsFlipped": false,
      "IsMatched": false
    },
    {
      "Id": 0,
      "ImagePath": "C:\\Facultate\\An 2\\Semestrul 2\\MAP\\MemoryGame\\MemoryGame\\bin\\Debug\\net8.0-windows\\Images\\Cars\\pexels-charles-kettor-268979-831475.jpg",
      "IsFlipped": false,
      "IsMatched": false
    }
  ]
}